{
	"cmake" : 
	{
		"generator" : 
		{
			"multiConfig" : false,
			"name" : "Ninja"
		},
		"paths" : 
		{
			"cmake" : "/home/haoyang/.local/share/JetBrains/Toolbox/apps/CLion/ch-0/223.8617.54/bin/cmake/linux/x64/bin/cmake",
			"cpack" : "/home/haoyang/.local/share/JetBrains/Toolbox/apps/CLion/ch-0/223.8617.54/bin/cmake/linux/x64/bin/cpack",
			"ctest" : "/home/haoyang/.local/share/JetBrains/Toolbox/apps/CLion/ch-0/223.8617.54/bin/cmake/linux/x64/bin/ctest",
			"root" : "/home/haoyang/.local/share/JetBrains/Toolbox/apps/CLion/ch-0/223.8617.54/bin/cmake/linux/x64/share/cmake-3.24"
		},
		"version" : 
		{
			"isDirty" : false,
			"major" : 3,
			"minor" : 24,
			"patch" : 2,
			"string" : "3.24.2",
			"suffix" : ""
		}
	},
	"objects" : 
	[
		{
			"jsonFile" : "codemodel-v2-fa6e4dfaf76e264a3ebd.json",
			"kind" : "codemodel",
			"version" : 
			{
				"major" : 2,
				"minor" : 4
			}
		},
		{
			"jsonFile" : "cache-v2-9ab306d81223d012d744.json",
			"kind" : "cache",
			"version" : 
			{
				"major" : 2,
				"minor" : 0
			}
		},
		{
			"jsonFile" : "cmakeFiles-v1-c3a454a4a72d9f127faa.json",
			"kind" : "cmakeFiles",
			"version" : 
			{
				"major" : 1,
				"minor" : 0
			}
		},
		{
			"jsonFile" : "toolchains-v1-99265b04de7ada3aac9e.json",
			"kind" : "toolchains",
			"version" : 
			{
				"major" : 1,
				"minor" : 0
			}
		}
	],
	"reply" : 
	{
		"cache-v2" : 
		{
			"jsonFile" : "cache-v2-9ab306d81223d012d744.json",
			"kind" : "cache",
			"version" : 
			{
				"major" : 2,
				"minor" : 0
			}
		},
		"cmakeFiles-v1" : 
		{
			"jsonFile" : "cmakeFiles-v1-c3a454a4a72d9f127faa.json",
			"kind" : "cmakeFiles",
			"version" : 
			{
				"major" : 1,
				"minor" : 0
			}
		},
		"codemodel-v2" : 
		{
			"jsonFile" : "codemodel-v2-fa6e4dfaf76e264a3ebd.json",
			"kind" : "codemodel",
			"version" : 
			{
				"major" : 2,
				"minor" : 4
			}
		},
		"toolchains-v1" : 
		{
			"jsonFile" : "toolchains-v1-99265b04de7ada3aac9e.json",
			"kind" : "toolchains",
			"version" : 
			{
				"major" : 1,
				"minor" : 0
			}
		}
	}
}
